patrowlassets/__init__.py
patrowlassets/cli.py
patrowlassets/main.py
patrowlassets/providers/__init__.py
patrowlassets/providers/aws.py
patrowlassets/providers/azure.py
patrowlassets/providers/ovh.py
PatrowlAssets-0.0.3.dist-info/LICENSE
PatrowlAssets-0.0.3.dist-info/METADATA
PatrowlAssets-0.0.3.dist-info/WHEEL
PatrowlAssets-0.0.3.dist-info/dependency_links.txt
PatrowlAssets-0.0.3.dist-info/entry_points.txt
PatrowlAssets-0.0.3.dist-info/top_level.txt
PatrowlAssets-0.0.3.dist-info/RECORD
