Metadata-Version: 2.1
Name: PatrowlAssets
Version: 0.0.3
Summary: Python API and CLI for extracting assets from Cloud and virtualized systems
Home-page: https://github.com/Patrowl/PatrowlAssets
Author: Nicolas Mattiocco
Author-email: nicolas@patrowl.io
License: MIT
Platform: UNKNOWN
Requires-Python: >=3.6
Requires-Dist: boto3 (==1.17.11)
Requires-Dist: botocore (==1.20.11)
Requires-Dist: certifi (==2020.12.5)
Requires-Dist: chardet (==4.0.0)
Requires-Dist: click (==7.1.2)
Requires-Dist: click-config-file (==0.6.0)
Requires-Dist: configobj (==5.0.6)
Requires-Dist: idna (==2.10)
Requires-Dist: jmespath (==0.10.0)
Requires-Dist: ovh (==0.5.0)
Requires-Dist: Patrowl4py (==1.1.3)
Requires-Dist: python-dateutil (==2.8.1)
Requires-Dist: requests (==2.25.1)
Requires-Dist: s3transfer (==0.3.4)
Requires-Dist: six (==1.15.0)
Requires-Dist: slugify (==0.0.1)
Requires-Dist: urllib3 (==1.26.3)
